bittrade_kraken_websocket/__init__.py
bittrade_kraken_websocket/channels/__init__.py
bittrade_kraken_websocket/channels/channels.py
bittrade_kraken_websocket/channels/models/__init__.py
bittrade_kraken_websocket/channels/models/message.py
bittrade_kraken_websocket/channels/models/ohlc.py
bittrade_kraken_websocket/channels/models/spread.py
bittrade_kraken_websocket/channels/models/ticker.py
bittrade_kraken_websocket/channels/models/trade.py
bittrade_kraken_websocket/channels/ohlc.py
bittrade_kraken_websocket/channels/open_orders.py
bittrade_kraken_websocket/channels/own_trades.py
bittrade_kraken_websocket/channels/payload.py
bittrade_kraken_websocket/channels/spread.py
bittrade_kraken_websocket/channels/subscribe.py
bittrade_kraken_websocket/channels/ticker.py
bittrade_kraken_websocket/channels/trade.py
bittrade_kraken_websocket/connection/__init__.py
bittrade_kraken_websocket/connection/connection_operators.py
bittrade_kraken_websocket/connection/enhanced_websocket.py
bittrade_kraken_websocket/connection/generic.py
bittrade_kraken_websocket/connection/private.py
bittrade_kraken_websocket/connection/public.py
bittrade_kraken_websocket/connection/reconnect.py
bittrade_kraken_websocket/connection/status.py
bittrade_kraken_websocket/development/__init__.py
bittrade_kraken_websocket/events/__init__.py
bittrade_kraken_websocket/events/add_order.py
bittrade_kraken_websocket/events/cancel_order.py
bittrade_kraken_websocket/events/edit_order.py
bittrade_kraken_websocket/events/events.py
bittrade_kraken_websocket/events/ids.py
bittrade_kraken_websocket/events/message.py
bittrade_kraken_websocket/events/models/__init__.py
bittrade_kraken_websocket/events/models/order.py
bittrade_kraken_websocket/events/request_response.py
bittrade_kraken_websocket/messages/__init__.py
bittrade_kraken_websocket/messages/filters/__init__.py
bittrade_kraken_websocket/messages/filters/kind.py
bittrade_kraken_websocket/messages/heartbeat.py
bittrade_kraken_websocket/messages/json.py
bittrade_kraken_websocket-0.3.11.dist-info/WHEEL
bittrade_kraken_websocket-0.3.11.dist-info/METADATA
bittrade_kraken_websocket-0.3.11.dist-info/RECORD
