Metadata-Version: 2.1
Name: bittrade-kraken-websocket
Version: 0.3.11
Summary: Reactive Websocket for Kraken
Home-page: https://github.com/TechSpaceAsia/bittrade-kraken-websocket
License: MIT
Author: mat
Author-email: matt@techspace.asia
Requires-Python: >=3.10,<4.0
Classifier: Development Status :: 3 - Alpha
Classifier: Intended Audience :: Developers
Classifier: License :: OSI Approved :: MIT License
Classifier: Programming Language :: Python :: 3
Classifier: Programming Language :: Python :: 3.10
Classifier: Programming Language :: Python :: 3.11
Classifier: Topic :: Office/Business :: Financial :: Investment
Classifier: Topic :: Software Development :: Libraries :: Python Modules
Requires-Dist: bittrade-kraken-rest (>=0.13.7,<0.14.0)
Requires-Dist: expression (>=4.2.2,<5.0.0)
Requires-Dist: orjson (>=3.8.3,<4.0.0)
Requires-Dist: pydantic (>=1.10.4,<2.0.0)
Requires-Dist: reactivex (>=4.0.4,<5.0.0)
Requires-Dist: websocket-client (>=1.4.2,<2.0.0)
Project-URL: Repository, https://github.com/TechSpaceAsia/bittrade-kraken-websocket
